mistex/__init__.py
mistex/__main__.py
mistex/footnotes.py
mistex/latex_renderer.py
mistex-0.0.1.dist-info/METADATA
mistex-0.0.1.dist-info/WHEEL
mistex-0.0.1.dist-info/top_level.txt
mistex-0.0.1.dist-info/RECORD
